pygenesis_django/__init__.py
pygenesis_django/admin.py
pygenesis_django/apps.py
pygenesis_django/info.py
pygenesis_django/models.py
pygenesis_django/package.py
pygenesis_django/tests.py
pygenesis_django/views.py
pygenesis_django/management/__init__.py
pygenesis_django/management/commands/__init__.py
pygenesis_django/management/commands/pygenesis_django_info.py
pygenesis_django/migrations/__init__.py
pygenesis_django-0.1.2.dist-info/LICENSE
pygenesis_django-0.1.2.dist-info/METADATA
pygenesis_django-0.1.2.dist-info/WHEEL
pygenesis_django-0.1.2.dist-info/top_level.txt
pygenesis_django-0.1.2.dist-info/RECORD
