Metadata-Version: 2.1
Name: pygenesis-django
Version: 0.1.2
Summary: Python Django package repository template
Home-page: https://github.com/libresource/pygenesis-django
Author: quillcraftsman
Author-email: quill@craftsman.lol
License: MIT
Project-URL: Documentation, https://pygenesis-django.libresource.info
Project-URL: Source, https://github.com/libresource/pygenesis-django
Project-URL: Tracker, https://github.com/libresource/pygenesis-django/issues
Project-URL: Release notes, https://github.com/libresource/pygenesis-django/releases
Project-URL: Changelog, https://github.com/libresource/pygenesis-django/releases
Project-URL: Download, https://pypi.org/project/pygenesis-django/
Keywords: python,django,package,template-repository
Classifier: Development Status :: 3 - Alpha
Classifier: Intended Audience :: Developers
Classifier: License :: OSI Approved :: MIT License
Classifier: Programming Language :: Python :: 3
Classifier: Environment :: Web Environment
Classifier: Framework :: Django
Classifier: Operating System :: OS Independent
Classifier: Topic :: Software Development
Classifier: Topic :: Software Development :: Libraries
Classifier: Topic :: Software Development :: Libraries :: Python Modules
Requires-Python: >=3
License-File: LICENSE
